ssl_eval/__init__.py
ssl_eval/data.py
ssl_eval/distributed.py
ssl_eval/early_stopping.py
ssl_eval/emb_memory_bank.py
ssl_eval/eval.py
ssl_eval/generator.py
ssl_eval/knn.py
ssl_eval/larc.py
ssl_eval/lin_eval.py
ssl_eval/pkbar.py
ssl_eval/snn.py
ssl_eval/store_eval.py
ssl_eval/utils.py
ssl_eval-0.1.7.dist-info/LICENSE
ssl_eval-0.1.7.dist-info/METADATA
ssl_eval-0.1.7.dist-info/WHEEL
ssl_eval-0.1.7.dist-info/top_level.txt
ssl_eval-0.1.7.dist-info/RECORD
